browser_history/__init__.py
browser_history/browser_types.py
browser_history/chrome.py
browser_history/firefox.py
browser_history/mcp_server.py
browser_history/safari.py
browser_history/sqlite.py
browser_history/toolbox.py
llm_tools_browser_history-0.3.0.dist-info/licenses/LICENSE.md
llm_tools_browser_history-0.3.0.dist-info/METADATA
llm_tools_browser_history-0.3.0.dist-info/WHEEL
llm_tools_browser_history-0.3.0.dist-info/entry_points.txt
llm_tools_browser_history-0.3.0.dist-info/top_level.txt
llm_tools_browser_history-0.3.0.dist-info/RECORD
