Metadata-Version: 2.4
Name: llm-tools-browser-history
Version: 0.3.0
Summary: MCP server for searching local browser history files. Also compatible with llm-tools.
Author-email: Dane Summers <dsummersl@gmail.com>
License: Apache-2.0
Classifier: Programming Language :: Python :: 3
Classifier: License :: OSI Approved
Classifier: Typing :: Typed
Requires-Python: >=3.11
License-File: LICENSE.md
Requires-Dist: click>=8.3.1
Requires-Dist: llm>=0.27.1
Requires-Dist: mcp>=1.0.0
Dynamic: license-file
